{
  "version": "experimental",
  "tags": [
    {
      "name": "control-description-sheet",
      "path": "./control-description-sheet.js",
      "description": "A web component to build a control description sheet.",
      "attributes": [
        {
          "name": "title",
          "description": "Title of the course",
          "type": "string"
        },
        {
          "name": "course",
          "description": "Course name or number",
          "type": "string"
        },
        {
          "name": "distance",
          "description": "Total distance of the course",
          "type": "string"
        },
        {
          "name": "elevation",
          "description": "Total elevation gain",
          "type": "string"
        },
        {
          "name": "finalDistance",
          "description": "Distance to the final control",
          "type": "string"
        }
      ],
      "properties": [
        {
          "name": "title",
          "attribute": "title",
          "description": "Title of the course",
          "type": "string"
        },
        {
          "name": "course",
          "attribute": "course",
          "description": "Course name or number",
          "type": "string"
        },
        {
          "name": "distance",
          "attribute": "distance",
          "description": "Total distance of the course",
          "type": "string"
        },
        {
          "name": "elevation",
          "attribute": "elevation",
          "description": "Total elevation gain",
          "type": "string"
        },
        {
          "name": "finalDistance",
          "attribute": "finalDistance",
          "description": "Distance to the final control",
          "type": "string"
        }
      ],
      "cssProperties": [
        {
          "name": "--primary",
          "description": "Color of the text, borders and symbols"
        },
        {
          "name": "--width",
          "description": "Width of the control sheet"
        },
        {
          "name": "--border-radius",
          "description": "Border radius of the outermost border"
        }
      ]
    },
    {
      "name": "control-description",
      "path": "./control-description-sheet.js",
      "description": "An element representing a control.",
      "attributes": [
        {
          "name": "code",
          "description": "Control code",
          "type": "string"
        },
        {
          "name": "which",
          "description": "Which feature",
          "type": "string"
        },
        {
          "name": "feature",
          "description": "Control feature",
          "type": "string"
        },
        {
          "name": "appearance",
          "description": "Control appearance",
          "type": "string"
        },
        {
          "name": "dimensions",
          "description": "Control dimensions",
          "type": "string"
        },
        {
          "name": "location",
          "description": "Control location",
          "type": "string"
        },
        {
          "name": "other",
          "description": "Other informaion about the control",
          "type": "string"
        }
      ],
      "properties": [
        {
          "name": "code",
          "attribute": "code",
          "description": "Control code",
          "type": "string"
        },
        {
          "name": "which",
          "attribute": "which",
          "description": "Which feature",
          "type": "string"
        },
        {
          "name": "feature",
          "attribute": "feature",
          "description": "Control feature",
          "type": "string"
        },
        {
          "name": "appearance",
          "attribute": "appearance",
          "description": "Control appearance",
          "type": "string"
        },
        {
          "name": "dimensions",
          "attribute": "dimensions",
          "description": "Control dimensions",
          "type": "string"
        },
        {
          "name": "location",
          "attribute": "location",
          "description": "Control location",
          "type": "string"
        },
        {
          "name": "other",
          "attribute": "other",
          "description": "Other informaion about the control",
          "type": "string"
        }
      ]
    }
  ]
}